{
	"animations": [
		{
			"loop": false,
			"offsets": [0, 0],
			"anim": "idle",
			"fps": 24,
			"name": "bambi idle",
			"indices": []
		},
		{
			"loop": false,
			"offsets": [-17, -32],
			"anim": "singDOWN",
			"fps": 24,
			"name": "bambi down",
			"indices": []
		},
		{
			"loop": false,
			"offsets": [-27, 34],
			"anim": "singUP",
			"fps": 24,
			"name": "bambi up",
			"indices": []
		},
		{
			"loop": false,
			"offsets": [68, 82],
			"anim": "singSmash",
			"fps": 24,
			"name": "bambi phone",
			"indices": []
		},
		{
			"offsets": [-4, 8],
			"loop": false,
			"fps": 24,
			"anim": "hey",
			"indices": [],
			"name": "bambi look"
		},
		{
			"loop": false,
			"offsets": [61, 3],
			"anim": "singLEFT",
			"fps": 24,
			"name": "bambi right",
			"indices": []
		},
		{
			"loop": false,
			"offsets": [-64, 6],
			"anim": "singRIGHT",
			"fps": 24,
			"name": "bambi left",
			"indices": []
		},
		{
			"loop": false,
			"offsets": [-10, 0],
			"anim": "singDOWNmiss",
			"fps": 24,
			"name": "miss down",
			"indices": []
		},
		{
			"loop": false,
			"offsets": [-27, 32],
			"anim": "singUPmiss",
			"fps": 24,
			"name": "miss up",
			"indices": []
		},
		{
			"loop": false,
			"offsets": [23, 14],
			"anim": "singLEFTmiss",
			"fps": 24,
			"name": "miss right",
			"indices": []
		},
		{
			"loop": false,
			"offsets": [-63, 15],
			"anim": "singRIGHTmiss",
			"fps": 24,
			"name": "miss left",
			"indices": []
		}
	],
	"vocals_file": "",
	"no_antialiasing": false,
	"image": "characters/bambi/bambiRemake",
	"position": [10, 460],
	"healthicon": "bambi-new",
	"flip_x": false,
	"healthbar_colors": [37, 191, 55],
	"camera_position": [-40, 0],
	"sing_duration": 4,
	"scale": 1,
	"_editor_isPlayer": true
}